echoregions/__init__.py
echoregions/core.py
echoregions/lines/__init__.py
echoregions/lines/lines.py
echoregions/lines/lines_parser.py
echoregions/regions2d/__init__.py
echoregions/regions2d/evr_writer.py
echoregions/regions2d/regions2d.py
echoregions/regions2d/regions2d_parser.py
echoregions/test_data/transect.evl
echoregions/test_data/transect.evr
echoregions/test_data/transect_BT_ET.evr
echoregions/test_data/transect_ET_RT.evr
echoregions/test_data/transect_RT_RT.evr
echoregions/test_data/transect_ST_ST.evr
echoregions/test_data/transect_empty.evr
echoregions/test_data/transect_missing_bbox.evr
echoregions/test_data/transect_multi_mask.evr
echoregions/test_data/transect.zarr/.zattrs
echoregions/test_data/transect.zarr/.zgroup
echoregions/test_data/transect.zarr/.zmetadata
echoregions/test_data/transect.zarr/Sv/.zarray
echoregions/test_data/transect.zarr/Sv/.zattrs
echoregions/test_data/transect.zarr/Sv/0.0.0
echoregions/test_data/transect.zarr/Sv/0.1.0
echoregions/test_data/transect.zarr/Sv/0.2.0
echoregions/test_data/transect.zarr/channel/.zarray
echoregions/test_data/transect.zarr/channel/.zattrs
echoregions/test_data/transect.zarr/channel/0
echoregions/test_data/transect.zarr/depth/.zarray
echoregions/test_data/transect.zarr/depth/.zattrs
echoregions/test_data/transect.zarr/depth/0
echoregions/test_data/transect.zarr/ping_time/.zarray
echoregions/test_data/transect.zarr/ping_time/.zattrs
echoregions/test_data/transect.zarr/ping_time/0
echoregions/test_data/transect.zarr/range_sample/.zarray
echoregions/test_data/transect.zarr/range_sample/.zattrs
echoregions/test_data/transect.zarr/range_sample/0
echoregions/tests/__init__.py
echoregions/tests/test_lines.py
echoregions/tests/test_regions2d.py
echoregions/tests/test_utils.py
echoregions/utils/__init__.py
echoregions/utils/api.py
echoregions/utils/io.py
echoregions/utils/time.py
echoregions-0.2.2.dist-info/licenses/LICENSE
echoregions-0.2.2.dist-info/METADATA
echoregions-0.2.2.dist-info/WHEEL
echoregions-0.2.2.dist-info/top_level.txt
echoregions-0.2.2.dist-info/RECORD
