Metadata-Version: 2.4
Name: echoregions
Version: 0.2.2
Summary: Parsers and functions for working with EVR and EVL files
Home-page: https://github.com/OSOceanAcoustics/echoregions
Author: Caesar Tuguinay
Author-email: ctuguina@uw.edu
Maintainer: Caesar Tuguinay
Maintainer-email: ctuguina@uw.edu
License: Apache License, Version 2.0
Platform: OS Independent
Classifier: Development Status :: 4 - Beta
Classifier: Environment :: Console
Classifier: Intended Audience :: Science/Research
Classifier: License :: OSI Approved :: Apache Software License
Classifier: Operating System :: OS Independent
Classifier: Programming Language :: Python
Classifier: Programming Language :: Python :: 3 :: Only
Classifier: Programming Language :: Python :: 3.10
Classifier: Programming Language :: Python :: 3.10
Classifier: Programming Language :: Python :: 3.12
Classifier: Topic :: Scientific/Engineering
Requires-Python: >=3.10
License-File: LICENSE
Requires-Dist: numpy>=1.21.0
Requires-Dist: pandas>=2.0.0
Requires-Dist: matplotlib
Requires-Dist: regionmask>=0.8.0
Requires-Dist: shapely>=2.0.0
Requires-Dist: zarr<3,>=2
Requires-Dist: netcdf4
Requires-Dist: scipy<1.15.2
Requires-Dist: xarray>=2024.11.0
Requires-Dist: dask
Dynamic: license-file
Dynamic: requires-dist
